calendar_view/__init__.py
calendar_view/calendar.py
calendar_view/__pycache__/__init__.cpython-313.pyc
calendar_view/config/__init__.py
calendar_view/config/i18n.py
calendar_view/config/style.py
calendar_view/config/__pycache__/__init__.cpython-313.pyc
calendar_view/config/__pycache__/i18n.cpython-313.pyc
calendar_view/core/__init__.py
calendar_view/core/calendar_events.py
calendar_view/core/calendar_grid.py
calendar_view/core/config.py
calendar_view/core/data.py
calendar_view/core/event.py
calendar_view/core/round_rectangle.py
calendar_view/core/time_utils.py
calendar_view/core/utils.py
calendar_view/core/__pycache__/__init__.cpython-313.pyc
calendar_view/core/__pycache__/config.cpython-313.pyc
calendar_view/core/__pycache__/time_utils.cpython-313.pyc
calendar_view/core/__pycache__/utils.cpython-313.pyc
calendar_view/resources/__init__.py
calendar_view/resources/fonts/LICENSE.txt
calendar_view/resources/fonts/Roboto-Regular.ttf
calendar_view/resources/fonts/__init__.py
calendar_view-2.5.0.dist-info/licenses/LICENSE
calendar_view-2.5.0.dist-info/METADATA
calendar_view-2.5.0.dist-info/WHEEL
calendar_view-2.5.0.dist-info/top_level.txt
calendar_view-2.5.0.dist-info/RECORD
