Metadata-Version: 2.4
Name: calendar-view
Version: 2.5.0
Summary: Library provides a graphical view of the calendar.
Home-page: https://github.com/sakhnevych/calendar-view
Author: Oleksandr Sakhnevych, Daniil Limariev
Author-email: o.sakhnevych@gmail.com, danillim02102003@gmail.com
Classifier: Programming Language :: Python :: 3
Classifier: License :: OSI Approved :: MIT License
Classifier: Operating System :: OS Independent
Requires-Python: >=3.6
License-File: LICENSE
Requires-Dist: Pillow
Dynamic: author
Dynamic: author-email
Dynamic: classifier
Dynamic: description
Dynamic: description-content-type
Dynamic: home-page
Dynamic: license-file
Dynamic: requires-dist
Dynamic: requires-python
Dynamic: summary
